crank/__init__.py
crank/async.py
crank/dom.py
crank/html.py
crankpy-0.2.0.dist-info/licenses/LICENSE
crankpy-0.2.0.dist-info/METADATA
crankpy-0.2.0.dist-info/WHEEL
crankpy-0.2.0.dist-info/top_level.txt
crankpy-0.2.0.dist-info/RECORD
