Metadata-Version: 2.4
Name: crankpy
Version: 0.2.0
Summary: Python Frontend Framework with Async/Generators, Powered by Crank.js
Author-email: Brian Kim <briankimpossible@gmail.com>
Maintainer-email: Brian Kim <briankimpossible@gmail.com>
License-Expression: MIT
Project-URL: Homepage, https://github.com/bikeshaving/crankpy
Project-URL: Repository, https://github.com/bikeshaving/crankpy
Project-URL: Documentation, https://github.com/bikeshaving/crankpy#readme
Project-URL: Bug Tracker, https://github.com/bikeshaving/crankpy/issues
Project-URL: JavaScript Core, https://crank.js.org
Keywords: crank,components,pyscript,pyodide,micropython,generators,ui,hyperscript,jsx,browser
Classifier: Development Status :: 3 - Alpha
Classifier: Intended Audience :: Developers
Classifier: Programming Language :: Python :: 3
Classifier: Programming Language :: Python :: 3.8
Classifier: Programming Language :: Python :: 3.9
Classifier: Programming Language :: Python :: 3.10
Classifier: Programming Language :: Python :: 3.11
Classifier: Programming Language :: Python :: 3.12
Classifier: Topic :: Software Development :: Libraries :: Python Modules
Classifier: Topic :: Internet :: WWW/HTTP :: Dynamic Content
Classifier: Environment :: Web Environment
Classifier: Framework :: AsyncIO
Classifier: Operating System :: OS Independent
Requires-Python: >=3.8
License-File: LICENSE
Requires-Dist: pyscript>=0.2.5
Provides-Extra: dev
Requires-Dist: pytest>=7.0; extra == "dev"
Requires-Dist: pytest-asyncio>=0.21.0; extra == "dev"
Requires-Dist: playwright>=1.40.0; extra == "dev"
Requires-Dist: build>=0.10.0; extra == "dev"
Requires-Dist: twine>=4.0.0; extra == "dev"
Requires-Dist: pytest-playwright>=0.5.2; extra == "dev"
Dynamic: license-file
